README.rst
gevent_helpers.py
setup.py
gevent_helpers.egg-info/PKG-INFO
gevent_helpers.egg-info/SOURCES.txt
gevent_helpers.egg-info/dependency_links.txt
gevent_helpers.egg-info/not-zip-safe
gevent_helpers.egg-info/top_level.txt