Metadata-Version: 1.0
Name: gevent-helpers
Version: 0.1.1
Summary: UNKNOWN
Home-page: https://github.com/wolever/gevent-helpers
Author: David Wolever
Author-email: david@wolever.net
License: BSD
Platform: UNKNOWN
Classifier: Development Status :: 4 - Beta
Classifier: Intended Audience :: Developers
Classifier: License :: OSI Approved :: BSD License
Classifier: Natural Language :: English
Classifier: Operating System :: OS Independent
Classifier: Programming Language :: Python
